{
  "version": 1,
  "serviceConfiguration": {
    "apiName": "trackerapp",
    "serviceName": "AppSync",
    "defaultAuthType": {
      "mode": "API_KEY",
      "expirationTime": 365,
      "apiKeyExpirationDate": "2024-10-23T13:58:18.622Z",
      "keyDescription": ""
    },
    "conflictResolution": {
      "defaultResolutionStrategy": {
        "type": "AUTOMERGE"
      },
      "perModelResolutionStrategy": [
        {
          "resolutionStrategy": {
            "type": "AUTOMERGE"
          },
          "entityName": "Activity"
        },
        {
          "resolutionStrategy": {
            "type": "AUTOMERGE"
          },
          "entityName": "ActivityDuration"
        }
      ]
    },
    "additionalAuthTypes": [
      {
        "mode": "AWS_IAM"
      },
      {
        "mode": "AMAZON_COGNITO_USER_POOLS",
        "cognitoUserPoolId": "authtrackerappd3bb5f5e"
      }
    ]
  }
}